app/__init__.py
app/ask.py
app/ask_enhanced.py
app/ask_v2.py
app/classic_main.py
app/config.py
app/console_interface.py
app/console_utils.py
app/database.py
app/main.py
app/model_manager.py
app/models.py
app/utils.py
app/api/__init__.py
app/api/anthropic.py
app/api/base.py
app/api/custom_openai.py
app/api/ollama.py
app/api/openai.py
app/ui/__init__.py
app/ui/borders.py
app/ui/chat_interface.py
app/ui/chat_list.py
app/ui/model_browser.py
app/ui/model_selector.py
app/ui/search.py
app/ui/settings.py
app/ui/styles.py
chat_console-0.5.95.dist-info/licenses/LICENSE
chat_console-0.5.95.dist-info/METADATA
chat_console-0.5.95.dist-info/WHEEL
chat_console-0.5.95.dist-info/entry_points.txt
chat_console-0.5.95.dist-info/top_level.txt
chat_console-0.5.95.dist-info/RECORD
