Metadata-Version: 2.4
Name: chat-console
Version: 0.5.95
Summary: A command-line interface for chatting with LLMs, storing chats and (future) rag interactions
Home-page: https://github.com/wazacraftrfid/chat-console
Author: Johnathan Greenaway
Author-email: john@fimbriata.dev
Classifier: Programming Language :: Python :: 3
Classifier: License :: OSI Approved :: MIT License
Classifier: Operating System :: OS Independent
Requires-Python: >=3.7
License-File: LICENSE
Requires-Dist: textual>=0.11.1
Requires-Dist: typer>=0.7.0
Requires-Dist: requests>=2.28.1
Requires-Dist: anthropic>=0.5.0
Requires-Dist: openai>=0.27.0
Requires-Dist: python-dotenv>=0.21.0
Requires-Dist: beautifulsoup4>=4.11.0
Requires-Dist: aiohttp>=3.8.0
Dynamic: author
Dynamic: author-email
Dynamic: classifier
Dynamic: description
Dynamic: description-content-type
Dynamic: home-page
Dynamic: license-file
Dynamic: requires-dist
Dynamic: requires-python
Dynamic: summary
